deproject/__init__.py
deproject/deproject.py
deproject/fieldstore.py
deproject/simplegraph.py
deproject/specstack.py
deproject-0.2.2.dist-info/LICENSE
deproject-0.2.2.dist-info/METADATA
deproject-0.2.2.dist-info/WHEEL
deproject-0.2.2.dist-info/top_level.txt
deproject-0.2.2.dist-info/RECORD
