Metadata-Version: 2.1
Name: deproject
Version: 0.2.2
Summary: Sherpa deprojection package (X-ray analysis of Galaxy Clusters, Groups, and Galaxies)
Home-page: https://deproject.readthedocs.io/
Author: Douglas Burke, Tom Aldcroft
Author-email: dburke.gw@gmail.com
License: BSD
Project-URL: Issue Tracker, https://github.com/sherpa-deproject/deproject/issues/
Project-URL: Source Code, https://github.com/sherpa-deproject/deproject/
Project-URL: Documentaion, https://deproject.readthedocs.io/
Keywords: deprojection,xray,3d,2d,plasma,Astrophysics,onion
Platform: Linux
Platform: Mac OS X
Classifier: Development Status :: 4 - Beta
Classifier: Intended Audience :: Science/Research
Classifier: License :: OSI Approved :: BSD License
Classifier: Programming Language :: Python :: 3.7
Classifier: Programming Language :: Python :: 3.8
Classifier: Programming Language :: Python :: 3.9
Classifier: Topic :: Scientific/Engineering :: Astronomy
Classifier: Topic :: Scientific/Engineering :: Physics
Requires-Python: ~=3.7
License-File: LICENSE
Requires-Dist: sherpa (>=4.14.0)
Requires-Dist: astropy
Requires-Dist: scipy
